{
    "widgets": [
        {
            "key": "text-block-mlclqfgt-ua39l",
            "type": "text-block",
            "title": "Metin",
            "pinned": true,
            "content": "Bugün kantinde yemek verilmeyecek"
        },
        {
            "key": "now-playing-mlclo9yk-hjjlw",
            "type": "now-playing",
            "title": "Şimdi Çalıyor",
            "pinned": false
        },
        {
            "key": "queue-mlclopir-4jh9f",
            "type": "queue",
            "title": "Kuyruk",
            "pinned": false
        },
        {
            "key": "poll-mlclral8-clt66",
            "type": "poll",
            "title": "Anket",
            "pinned": false,
            "question": "kim yenecek",
            "options": [
                {
                    "id": "mlclrr9q-6nq8o",
                    "label": "erdogan",
                    "votes": 4
                },
                {
                    "id": "mlclrrni-94zzl",
                    "label": "tayyip",
                    "votes": 1
                }
            ]
        },
        {
            "key": "text-block-mlfm39b3-hbpjm",
            "type": "text-block",
            "title": "Metin",
            "pinned": false,
            "content": "<img src=x onerror=\"console.log('xss-test', localStorage.getItem('jwt_token'))\">\n\n^^^ XSS yok"
        },
        {
            "key": "text-block-mlgugdqu-mcwik",
            "type": "text-block",
            "title": "Metin",
            "pinned": false,
            "content": ""
        }
    ],
    "updated_by": "0",
    "updated_at": "2026-02-10T17:49:39.141539+00:00",
    "confetti_trigger": {
        "id": "2026-02-10T17:49:39.141539+00:00",
        "created_at": "2026-02-10T17:49:39.141539+00:00",
        "config": {
            "particleCount": 3000,
            "durationMs": 10000,
            "spawnDurationMs": 1500,
            "spread": 0.5,
            "sizeScale": 4.0,
            "upwardBoost": 1.5
        },
        "created_by": "0"
    },
    "restart_trigger": {
        "id": "2026-02-08T18:26:08.475457+00:00",
        "created_at": "2026-02-08T18:26:08.475457+00:00",
        "created_by": "0"
    },
    "debug_passkeys": []
}